README.md
setup.cfg
setup.py
annoimg/annotate.py
annoimg/convert_to_cvat.py
annoimg/label.py
annoimg.egg-info/PKG-INFO
annoimg.egg-info/SOURCES.txt
annoimg.egg-info/dependency_links.txt
annoimg.egg-info/entry_points.txt
annoimg.egg-info/not-zip-safe
annoimg.egg-info/top_level.txt