Metadata-Version: 2.1
Name: annoimg
Version: 0.1
Summary: Semi-auto annotation images using SAM2
Author-email: aleksandr.bakhshiev@compvisionsys.com
